running_formulas_mcp/__init__.py
running_formulas_mcp/server.py
running_formulas_mcp/core/__init__.py
running_formulas_mcp/core/conversions.py
running_formulas_mcp/core/formatting.py
running_formulas_mcp/formulas/__init__.py
running_formulas_mcp/formulas/daniels.py
running_formulas_mcp/formulas/riegel.py
running_formulas_mcp-0.2.0.dist-info/METADATA
running_formulas_mcp-0.2.0.dist-info/WHEEL
running_formulas_mcp-0.2.0.dist-info/entry_points.txt
running_formulas_mcp-0.2.0.dist-info/licenses/LICENSE
running_formulas_mcp-0.2.0.dist-info/RECORD
