Metadata-Version: 2.4
Name: running-formulas-mcp
Version: 0.2.0
Summary: An MCP server that calculates well-known running formulas
Author: Stev Witzel
License: MIT
License-File: LICENSE
Requires-Python: >=3.13
Requires-Dist: fastmcp
